CHANGELOG.txt
LICENCE.txt
MANIFEST.in
README.txt
setup.py
simplelist/__init__.py
simplelist/list.txt
simplelist/listfromtxt.py
simplelist/lists.py
simplelist/txtfromlist.py
simplelist.egg-info/PKG-INFO
simplelist.egg-info/SOURCES.txt
simplelist.egg-info/dependency_links.txt
simplelist.egg-info/top_level.txt
venv/bin/rst2html.py
venv/bin/rst2html4.py
venv/bin/rst2html5.py
venv/bin/rst2latex.py
venv/bin/rst2man.py
venv/bin/rst2odt.py
venv/bin/rst2odt_prepstyles.py
venv/bin/rst2pseudoxml.py
venv/bin/rst2s5.py
venv/bin/rst2xetex.py
venv/bin/rst2xml.py
venv/bin/rstpep2html.py
venv/lib/python3.9/site-packages/pyparsing.py
venv/lib/python3.9/site-packages/six.py
venv/lib/python3.9/site-packages/zipp.py
venv/lib/python3.9/site-packages/Pygments-2.9.0.dist-info/entry_points.txt
venv/lib/python3.9/site-packages/Pygments-2.9.0.dist-info/top_level.txt
venv/lib/python3.9/site-packages/_distutils_hack/__init__.py
venv/lib/python3.9/site-packages/_distutils_hack/override.py
venv/lib/python3.9/site-packages/bleach/__init__.py
venv/lib/python3.9/site-packages/bleach/callbacks.py
venv/lib/python3.9/site-packages/bleach/html5lib_shim.py
venv/lib/python3.9/site-packages/bleach/linkifier.py
venv/lib/python3.9/site-packages/bleach/sanitizer.py
venv/lib/python3.9/site-packages/bleach/utils.py
venv/lib/python3.9/site-packages/bleach-3.3.0.dist-info/top_level.txt
venv/lib/python3.9/site-packages/bleach/_vendor/__init__.py
venv/lib/python3.9/site-packages/bleach/_vendor/vendor.txt
venv/lib/python3.9/site-packages/bleach/_vendor/Django-1.11.29.dist-info/entry_points.txt
venv/lib/python3.9/site-packages/bleach/_vendor/Django-1.11.29.dist-info/top_level.txt
venv/lib/python3.9/site-packages/bleach/_vendor/django/__init__.py
venv/lib/python3.9/site-packages/bleach/_vendor/django/core/__init__.py
venv/lib/python3.9/site-packages/bleach/_vendor/django/core/validators.py
venv/lib/python3.9/site-packages/bleach/_vendor/html5lib/__init__.py
venv/lib/python3.9/site-packages/bleach/_vendor/html5lib/_ihatexml.py
venv/lib/python3.9/site-packages/bleach/_vendor/html5lib/_inputstream.py
venv/lib/python3.9/site-packages/bleach/_vendor/html5lib/_tokenizer.py
venv/lib/python3.9/site-packages/bleach/_vendor/html5lib/_utils.py
venv/lib/python3.9/site-packages/bleach/_vendor/html5lib/constants.py
venv/lib/python3.9/site-packages/bleach/_vendor/html5lib/html5parser.py
venv/lib/python3.9/site-packages/bleach/_vendor/html5lib/serializer.py
venv/lib/python3.9/site-packages/bleach/_vendor/html5lib-1.1.dist-info/top_level.txt
venv/lib/python3.9/site-packages/bleach/_vendor/html5lib/_trie/__init__.py
venv/lib/python3.9/site-packages/certifi-2020.12.5.dist-info/top_level.txt
venv/lib/python3.9/site-packages/chardet-4.0.0.dist-info/entry_points.txt
venv/lib/python3.9/site-packages/chardet-4.0.0.dist-info/top_level.txt
venv/lib/python3.9/site-packages/colorama-0.4.4.dist-info/LICENSE.txt
venv/lib/python3.9/site-packages/colorama-0.4.4.dist-info/top_level.txt
venv/lib/python3.9/site-packages/docutils-0.17.1.dist-info/COPYING.txt
venv/lib/python3.9/site-packages/docutils-0.17.1.dist-info/top_level.txt
venv/lib/python3.9/site-packages/idna-2.10.dist-info/top_level.txt
venv/lib/python3.9/site-packages/importlib_metadata-4.0.1.dist-info/top_level.txt
venv/lib/python3.9/site-packages/keyring-23.0.1.dist-info/entry_points.txt
venv/lib/python3.9/site-packages/keyring-23.0.1.dist-info/top_level.txt
venv/lib/python3.9/site-packages/list-0.0.1-py3.9.egg-info/SOURCES.txt
venv/lib/python3.9/site-packages/list-0.0.1-py3.9.egg-info/dependency_links.txt
venv/lib/python3.9/site-packages/list-0.0.1-py3.9.egg-info/installed-files.txt
venv/lib/python3.9/site-packages/list-0.0.1-py3.9.egg-info/top_level.txt
venv/lib/python3.9/site-packages/numpy-1.20.3.dist-info/LICENSE.txt
venv/lib/python3.9/site-packages/numpy-1.20.3.dist-info/LICENSES_bundled.txt
venv/lib/python3.9/site-packages/numpy-1.20.3.dist-info/entry_points.txt
venv/lib/python3.9/site-packages/numpy-1.20.3.dist-info/top_level.txt
venv/lib/python3.9/site-packages/packaging-20.9.dist-info/top_level.txt
venv/lib/python3.9/site-packages/pandas-1.2.4.dist-info/entry_points.txt
venv/lib/python3.9/site-packages/pandas-1.2.4.dist-info/top_level.txt
venv/lib/python3.9/site-packages/pip-21.1.2.dist-info/LICENSE.txt
venv/lib/python3.9/site-packages/pip-21.1.2.dist-info/entry_points.txt
venv/lib/python3.9/site-packages/pip-21.1.2.dist-info/top_level.txt
venv/lib/python3.9/site-packages/pkginfo-1.7.0.dist-info/LICENSE.txt
venv/lib/python3.9/site-packages/pkginfo-1.7.0.dist-info/entry_points.txt
venv/lib/python3.9/site-packages/pkginfo-1.7.0.dist-info/top_level.txt
venv/lib/python3.9/site-packages/pyparsing-2.4.7.dist-info/top_level.txt
venv/lib/python3.9/site-packages/python_dateutil-2.8.1.dist-info/top_level.txt
venv/lib/python3.9/site-packages/pytz-2021.1.dist-info/LICENSE.txt
venv/lib/python3.9/site-packages/pytz-2021.1.dist-info/top_level.txt
venv/lib/python3.9/site-packages/readme_renderer-29.0.dist-info/entry_points.txt
venv/lib/python3.9/site-packages/readme_renderer-29.0.dist-info/top_level.txt
venv/lib/python3.9/site-packages/requests-2.25.1.dist-info/top_level.txt
venv/lib/python3.9/site-packages/requests_toolbelt-0.9.1.dist-info/top_level.txt
venv/lib/python3.9/site-packages/rfc3986-1.5.0.dist-info/top_level.txt
venv/lib/python3.9/site-packages/setuptools-56.2.0.dist-info/dependency_links.txt
venv/lib/python3.9/site-packages/setuptools-56.2.0.dist-info/entry_points.txt
venv/lib/python3.9/site-packages/setuptools-56.2.0.dist-info/top_level.txt
venv/lib/python3.9/site-packages/simplelist-0.0.2-py3.9.egg-info/SOURCES.txt
venv/lib/python3.9/site-packages/simplelist-0.0.2-py3.9.egg-info/dependency_links.txt
venv/lib/python3.9/site-packages/simplelist-0.0.2-py3.9.egg-info/installed-files.txt
venv/lib/python3.9/site-packages/simplelist-0.0.2-py3.9.egg-info/top_level.txt
venv/lib/python3.9/site-packages/six-1.16.0.dist-info/top_level.txt
venv/lib/python3.9/site-packages/tqdm-4.60.0.dist-info/entry_points.txt
